vending_machine/rtl/fsm_vending_machine.v
module fsm_vending_machine (
    input  clk, reset, coin_5, coin_10, coin_25, req_item_a, req_item_b,

    output reg dispense_a, dispense_b, insufficient_funds,
    
    output reg [7:0] change_returned,

    output reg [7:0] total_funds
);

   
    localparam [7:0] PRICE_A = 8'd15;
    localparam [7:0] PRICE_B = 8'd40;

    localparam [2:0]
        IDLE     = 3'd0,
        ADD_COIN = 3'd1,
        CHECK_A  = 3'd2,
        CHECK_B  = 3'd3,
        VEND_A   = 3'd4,
        VEND_B   = 3'd5,
        WARN     = 3'd6;

    reg [2:0] current_state;
    reg [2:0] next_state;


    reg ctrl_add_5;
    reg ctrl_add_10;
    reg ctrl_add_25;
    reg ctrl_clear_funds;


    wire funds_ok_a;
    wire funds_ok_b;

    assign funds_ok_a = (total_funds >= PRICE_A);
    assign funds_ok_b = (total_funds >= PRICE_B);

   

    always @(posedge clk or posedge reset) begin

        if (reset) begin
            total_funds <= 8'd0;
        end

        else begin

            
            if (ctrl_clear_funds) begin
                total_funds <= 8'd0;
            end

            else if (ctrl_add_25) begin
                total_funds <= total_funds + 8'd25;
            end

            else if (ctrl_add_10) begin
                total_funds <= total_funds + 8'd10;
            end

            else if (ctrl_add_5) begin
                total_funds <= total_funds + 8'd5;
            end
        end
    end

    always @(posedge clk or posedge reset) begin

        if (reset) begin
            current_state <= IDLE;
        end

        else begin
            current_state <= next_state;
        end

    end



    always @(*) begin

        // Default
        next_state = current_state;

        case (current_state)

            IDLE: begin

                if (coin_5 || coin_10 || coin_25) begin
                    next_state = ADD_COIN;
                end

                else if (req_item_a) begin
                    next_state = CHECK_A;
                end

                else if (req_item_b) begin
                    next_state = CHECK_B;
                end

                else begin
                    next_state = IDLE;
                end

            end

            ADD_COIN: begin
                next_state = IDLE;
            end

            CHECK_A: begin

                if (funds_ok_a)
                    next_state = VEND_A;
                else
                    next_state = WARN;

            end

            CHECK_B: begin

                if (funds_ok_b)
                    next_state = VEND_B;
                else
                    next_state = WARN;

            end

            VEND_A: begin
                next_state = IDLE;
            end

            VEND_B: begin
                next_state = IDLE;
            end

            WARN: begin
                next_state = IDLE;
            end

            default: begin
                next_state = IDLE;
            end

        endcase

    end

    always @(*) begin

        dispense_a         = 1'b0;
        dispense_b         = 1'b0;
        insufficient_funds = 1'b0;

        ctrl_add_5       = 1'b0;
        ctrl_add_10      = 1'b0;
        ctrl_add_25      = 1'b0;
        ctrl_clear_funds = 1'b0;

        

        case (current_state)

            

            ADD_COIN: begin

                

                if (coin_25) begin
                    ctrl_add_25 = 1'b1;
                end

                else if (coin_10) begin
                    ctrl_add_10 = 1'b1;
                end

                else if (coin_5) begin
                    ctrl_add_5 = 1'b1;
                end

            end

            

            VEND_A: begin

                dispense_a = 1'b1;

                
                ctrl_clear_funds = 1'b1;

            end

            // =================================================
            // VEND B
            // =================================================

            VEND_B: begin

                dispense_b = 1'b1;

                
                ctrl_clear_funds = 1'b1;

            end

            WARN: begin

                insufficient_funds = 1'b1;

            end

            default: begin
                
            end

        endcase

    end

    
    always @(posedge clk or posedge reset) begin

        if (reset) begin
            change_returned <= 8'd0;
        end

        else begin

            if (current_state == VEND_A) begin

                change_returned <= total_funds - PRICE_A;

            end

            else if (current_state == VEND_B) begin

                change_returned <= total_funds - PRICE_B;

            end

            else if (current_state == IDLE) begin
              
                change_returned <= change_returned;

            end

        end

    end

endmodule

vending_machine/testbench/tb_fsm_vending_machine.v
`timescale 1ns/1ps

module tb_fsm_vending_machine;
    reg clk;
    reg reset;

    reg coin_5;
    reg coin_10;
    reg coin_25;

    reg req_item_a;
    reg req_item_b;


    wire dispense_a;
    wire dispense_b;
    wire insufficient_funds;
    wire [7:0] change_returned;
    wire [7:0] total_funds;


    fsm_vending_machine DUT (

        .clk(clk),
        .reset(reset),

        .coin_5(coin_5),
        .coin_10(coin_10),
        .coin_25(coin_25),

        .req_item_a(req_item_a),
        .req_item_b(req_item_b),

        .dispense_a(dispense_a),
        .dispense_b(dispense_b),
        .insufficient_funds(insufficient_funds),
        .change_returned(change_returned),
        .total_funds(total_funds)

    );

    initial begin

        clk = 1'b0;

        forever #5 clk = ~clk;

    end
    
    initial begin

        $dumpfile("vending_machine.vcd");
        $dumpvars(0, tb_fsm_vending_machine);

        reset = 1'b0;

        coin_5  = 1'b0;
        coin_10 = 1'b0;
        coin_25 = 1'b0;

        req_item_a = 1'b0;
        req_item_b = 1'b0;

    end


    initial begin

        
        // TEST 1: RESET
        $display("========================================");
        $display("TEST 1: RESET");
        $display("========================================");

        reset = 1'b1;

        #10;

        reset = 1'b0;

        #10;

        $display("Total funds = %d", total_funds);

        // TEST 2: INSERT ₹5

        $display("========================================");
        $display("TEST 2: INSERT ₹5");
        $display("========================================");

        coin_5 = 1'b1;

        #10;

        coin_5 = 1'b0;

        #10;

        $display("Total funds = %d", total_funds);


        
        // TEST 3: INSERT ₹10
        // Total should become ₹15

        $display("========================================");
        $display("TEST 3: INSERT ₹10");
        $display("========================================");

        coin_10 = 1'b1;

        #10;

        coin_10 = 1'b0;

        #10;

        $display("Total funds = %d", total_funds);

        // TEST 4: BUY ITEM A
        // Price A = ₹15
        // Expected:
        // dispense_a = 1
        // change = 0
        // total_funds = 0

        $display("========================================");
        $display("TEST 4: BUY ITEM A");
        $display("========================================");

        req_item_a = 1'b1;

        #10;

        req_item_a = 1'b0;

        #20;

        $display("Dispense A       = %b", dispense_a);
        $display("Change returned  = %d", change_returned);
        $display("Total funds      = %d", total_funds);


        
        // TEST 5: INSERT ₹25
        

        $display("========================================");
        $display("TEST 5: INSERT ₹25");
        $display("========================================");

        coin_25 = 1'b1;

        #10;

        coin_25 = 1'b0;

        #10;

        $display("Total funds = %d", total_funds);


        
        // TEST 6: BUY ITEM A WITH ₹25
        // Expected change = ₹10
        
        $display("========================================");
        $display("TEST 6: BUY ITEM A WITH ₹25");
        $display("========================================");

        req_item_a = 1'b1;

        #10;

        req_item_a = 1'b0;

        #20;

        $display("Dispense A       = %b", dispense_a);
        $display("Change returned  = %d", change_returned);
        $display("Total funds      = %d", total_funds);

        // TEST 7: INSERT ₹40

        $display("========================================");
        $display("TEST 7: INSERT ₹40");
        $display("========================================");

        coin_25 = 1'b1;

        #10;

        coin_25 = 1'b0;

        #10;

        coin_10 = 1'b1;

        #10;

        coin_10 = 1'b0;

        #10;

        coin_5 = 1'b1;

        #10;

        coin_5 = 1'b0;

        #10;

        $display("Total funds = %d", total_funds);


        // TEST 8: BUY ITEM B
        // Price B = ₹40
        // Expected:
        // dispense_b = 1
        // change = 0

        $display("========================================");
        $display("TEST 8: BUY ITEM B");
        $display("========================================");

        req_item_b = 1'b1;

        #10;

        req_item_b = 1'b0;

        #20;

        $display("Dispense B       = %b", dispense_b);
        $display("Change returned  = %d", change_returned);
        $display("Total funds      = %d", total_funds);


        
        // TEST 9: INSUFFICIENT FUNDS
        // Insert ₹10
        // Request B (₹40)

        $display("========================================");
        $display("TEST 9: INSUFFICIENT FUNDS");
        $display("========================================");

        coin_10 = 1'b1;

        #10;

        coin_10 = 1'b0;

        #10;

        req_item_b = 1'b1;

        #10;

        req_item_b = 1'b0;

        #20;

        $display("Insufficient funds = %b", insufficient_funds);
        $display("Total funds        = %d", total_funds);


        // TEST 10: ADD MORE MONEY AFTER INSUFFICIENT FUNDS
        // Existing = ₹10
        // Add ₹25 + ₹5
        // Total = ₹40
        $display("========================================");
        $display("TEST 10: ADD MORE MONEY");
        $display("========================================");

        coin_25 = 1'b1;

        #10;

        coin_25 = 1'b0;

        #10;

        coin_5 = 1'b1;

        #10;

        coin_5 = 1'b0;

        #10;

        $display("Total funds = %d", total_funds);


        
        // TEST 11: BUY ITEM B AFTER ADDING MONEY
    

        $display("========================================");
        $display("TEST 11: BUY ITEM B");
        $display("========================================");

        req_item_b = 1'b1;

        #10;

        req_item_b = 1'b0;

        #20;

        $display("Dispense B       = %b", dispense_b);
        $display("Change returned  = %d", change_returned);
        $display("Total funds      = %d", total_funds);


        
        // END SIMULATION

        $display("========================================");
        $display("ALL TESTS COMPLETED");
        $display("========================================");

        #20;

        $finish;

    end


    
    // 7. MONITOR IMPORTANT SIGNALS

    initial begin

        $monitor(
            "TIME=%0t | CLK=%b | RESET=%b | COINS=%b%b%b | REQ_A=%b | REQ_B=%b | FUNDS=%d | DISP_A=%b | DISP_B=%b | WARN=%b | CHANGE=%d",
            $time,
            clk,
            reset,
            coin_25,
            coin_10,
            coin_5,
            req_item_a,
            req_item_b,
            total_funds,
            dispense_a,
            dispense_b,
            insufficient_funds,
            change_returned
        );

    end

endmodule

vending_machine/sim/vending_machine.vcd
$date
	Wed Aug 26 19:50:07 2026
$end
$version
	Icarus Verilog
$end
$timescale
	1ps
$end
$scope module tb_fsm_vending_machine $end
$var wire 8 ! change_returned [7:0] $end
$var wire 1 " dispense_a $end
$var wire 1 # dispense_b $end
$var wire 1 $ insufficient_funds $end
$var wire 8 % total_funds [7:0] $end
$var reg 1 & clk $end
$var reg 1 ' coin_10 $end
$var reg 1 ( coin_25 $end
$var reg 1 ) coin_5 $end
$var reg 1 * req_item_a $end
$var reg 1 + req_item_b $end
$var reg 1 , reset $end
$scope module DUT $end
$var wire 1 - clk $end
$var wire 1 . coin_10 $end
$var wire 1 / coin_25 $end
$var wire 1 0 coin_5 $end
$var wire 1 1 funds_ok_a $end
$var wire 1 2 funds_ok_b $end
$var wire 1 3 req_item_a $end
$var wire 1 4 req_item_b $end
$var wire 1 5 reset $end
$var reg 8 6 change_returned [7:0] $end
$var reg 1 7 ctrl_add_10 $end
$var reg 1 8 ctrl_add_25 $end
$var reg 1 9 ctrl_add_5 $end
$var reg 1 : ctrl_clear_funds $end
$var reg 3 ; current_state [2:0] $end
$var reg 1 < dispense_a $end
$var reg 1 = dispense_b $end
$var reg 1 > insufficient_funds $end
$var reg 3 ? next_state [2:0] $end
$var reg 8 @ total_funds [7:0] $end
$upscope $end
$upscope $end
$enddefinitions $end
#0
$dumpvars
b0 @
b0 ?
0>
0=
0<
b0 ;
0:
09
08
07
b0 6
15
04
03
02
01
00
0/
0.
0-
1,
0+
0*
0)
0(
0'
0&
b0 %
0$
0#
0"
b0 !
$end
#5000
1&
1-
#10000
0&
0-
0,
05
#15000
1&
1-
#20000
b1 ?
0&
0-
1)
10
#25000
19
b0 ?
b1 ;
1&
1-
#30000
09
b0 ?
0&
0-
0)
00
#35000
b0 ;
1&
1-
#40000
b1 ?
0&
0-
1'
1.
#45000
17
b0 ?
b1 ;
1&
1-
#50000
07
b0 ?
0&
0-
0'
0.
#55000
b0 ;
1&
1-
#60000
b10 ?
0&
0-
1*
13
#65000
b110 ?
b10 ;
1&
1-
#70000
b110 ?
0&
0-
0*
03
#75000
1>
1$
b0 ?
b110 ;
1&
1-
#80000
0&
0-
#85000
0>
0$
b0 ;
1&
1-
#90000
b1 ?
0&
0-
1(
1/
#95000
18
b0 ?
b1 ;
1&
1-
#100000
08
b0 ?
0&
0-
0(
0/
#105000
b0 ;
1&
1-
#110000
b10 ?
0&
0-
1*
13
#115000
b110 ?
b10 ;
1&
1-
#120000
b110 ?
0&
0-
0*
03
#125000
1>
1$
b0 ?
b110 ;
1&
1-
#130000
0&
0-
#135000
0>
0$
b0 ;
1&
1-
#140000
b1 ?
0&
0-
1(
1/
#145000
18
b0 ?
b1 ;
1&
1-
#150000
08
b0 ?
0&
0-
0(
0/
#155000
b0 ;
1&
1-
#160000
b1 ?
0&
0-
1'
1.
#165000
17
b0 ?
b1 ;
1&
1-
#170000
07
b0 ?
0&
0-
0'
0.
#175000
b0 ;
1&
1-
#180000
b1 ?
0&
0-
1)
10
#185000
19
b0 ?
b1 ;
1&
1-
#190000
09
b0 ?
0&
0-
0)
00
#195000
b0 ;
1&
1-
#200000
b11 ?
0&
0-
1+
14
#205000
b110 ?
b11 ;
1&
1-
#210000
b110 ?
0&
0-
0+
04
#215000
1>
1$
b0 ?
b110 ;
1&
1-
#220000
0&
0-
#225000
0>
0$
b0 ;
1&
1-
#230000
b1 ?
0&
0-
1'
1.
#235000
17
b0 ?
b1 ;
1&
1-
#240000
07
b0 ?
0&
0-
0'
0.
#245000
b0 ;
1&
1-
#250000
b11 ?
0&
0-
1+
14
#255000
b110 ?
b11 ;
1&
1-
#260000
b110 ?
0&
0-
0+
04
#265000
1>
1$
b0 ?
b110 ;
1&
1-
#270000
0&
0-
#275000
0>
0$
b0 ;
1&
1-
#280000
b1 ?
0&
0-
1(
1/
#285000
18
b0 ?
b1 ;
1&
1-
#290000
08
b0 ?
0&
0-
0(
0/
#295000
b0 ;
1&
1-
#300000
b1 ?
0&
0-
1)
10
#305000
19
b0 ?
b1 ;
1&
1-
#310000
09
b0 ?
0&
0-
0)
00
#315000
b0 ;
1&
1-
#320000
b11 ?
0&
0-
1+
14
#325000
b110 ?
b11 ;
1&
1-
#330000
b110 ?
0&
0-
0+
04
#335000
1>
1$
b0 ?
b110 ;
1&
1-
#340000
0&
0-
#345000
0>
0$
b0 ;
1&
1-
